colorutilsqt/__init__.py
colorutilsqt/converter.py
colorutilsqt/terminal.py
colorutilsqt-0.1.4.dist-info/licenses/LICENSE
colorutilsqt-0.1.4.dist-info/METADATA
colorutilsqt-0.1.4.dist-info/WHEEL
colorutilsqt-0.1.4.dist-info/top_level.txt
colorutilsqt-0.1.4.dist-info/RECORD
