Metadata-Version: 2.4
Name: colorutilsqt
Version: 0.1.4
Summary: A simple library to convert and print colors in terminal
Home-page: https://github.com/Quinosaur/pycolortools
Author: Quinten Teusink
Classifier: Programming Language :: Python :: 3
Classifier: License :: OSI Approved :: MIT License
Classifier: Operating System :: OS Independent
Requires-Python: >=3.6
License-File: LICENSE
Dynamic: author
Dynamic: classifier
Dynamic: description
Dynamic: description-content-type
Dynamic: home-page
Dynamic: license-file
Dynamic: requires-python
Dynamic: summary
